[{"30000": [{"count": 1, "source": 30000, "target": 30070}, {"count": 3, "source": 30000, "target": 30067}], "30001": [], "30002": [{"count": 1, "source": 30002, "target": 30021}, {"count": 1, "source": 30002, "target": 30096}, {"count": 1, "source": 30002, "target": 30044}, {"count": 1, "source": 30002, "target": 30076}], "30003": [{"count": 1, "source": 30003, "target": 30026}, {"count": 1, "source": 30003, "target": 30015}], "30004": [{"count": 1, "source": 30004, "target": 30069}], "30005": [], "30006": [], "30007": [], "30008": [{"count": 1, "source": 30008, "target": 30116}, {"count": 1, "source": 30008, "target": 30012}, {"count": 1, "source": 30008, "target": 30103}], "30009": [{"count": 1, "source": 30009, "target": 30062}, {"count": 1, "source": 30009, "target": 30077}], "30010": [{"count": 1, "source": 30010, "target": 30057}], "30011": [], "30012": [{"count": 3, "source": 30012, "target": 30096}], "30013": [{"count": 1, "source": 30013, "target": 30057}], "30014": [], "30015": [{"count": 1, "source": 30015, "target": 30126}], "30016": [], "30017": [{"count": 1, "source": 30017, "target": 30114}], "30018": [], "30019": [], "30020": [{"count": 1, "source": 30020, "target": 30112}], "30021": [{"count": 2, "source": 30021, "target": 30031}], "30022": [{"count": 1, "source": 30022, "target": 30003}, {"count": 1, "source": 30022, "target": 30077}], "30023": [{"count": 1, "source": 30023, "target": 30057}, {"count": 2, "source": 30023, "target": 30003}, {"count": 1, "source": 30023, "target": 30066}], "30024": [], "30025": [{"count": 2, "source": 30025, "target": 30124}], "30026": [{"count": 2, "source": 30026, "target": 30097}, {"count": 1, "source": 30026, "target": 30114}, {"count": 1, "source": 30026, "target": 30104}], "30027": [{"count": 1, "source": 30027, "target": 30101}, {"count": 1, "source": 30027, "target": 30103}], "30028": [], "30029": [], "30030": [], "30031": [], "30032": [{"count": 1, "source": 30032, "target": 30092}], "30033": [{"count": 1, "source": 30033, "target": 30058}, {"count": 1, "source": 30033, "target": 30076}], "30034": [{"count": 1, "source": 30034, "target": 30065}, {"count": 1, "source": 30034, "target": 30108}, {"count": 1, "source": 30034, "target": 30039}, {"count": 1, "source": 30034, "target": 30160}], "30035": [{"count": 1, "source": 30035, "target": 30025}], "30036": [], "30037": [{"count": 2, "source": 30037, "target": 30094}, {"count": 1, "source": 30037, "target": 30089}, {"count": 1, "source": 30037, "target": 30078}], "30038": [{"count": 1, "source": 30038, "target": 30054}], "30039": [{"count": 1, "source": 30039, "target": 30084}, {"count": 1, "source": 30039, "target": 30124}, {"count": 2, "source": 30039, "target": 30101}], "30040": [{"count": 4, "source": 30040, "target": 30104}], "30041": [{"count": 1, "source": 30041, "target": 30084}, {"count": 1, "source": 30041, "target": 30058}], "30042": [{"count": 1, "source": 30042, "target": 30070}], "30043": [], "30044": [{"count": 1, "source": 30044, "target": 30002}, {"count": 3, "source": 30044, "target": 30144}], "30045": [{"count": 1, "source": 30045, "target": 30091}, {"count": 1, "source": 30045, "target": 30142}], "30046": [], "30047": [], "30048": [{"count": 1, "source": 30048, "target": 30096}, {"count": 2, "source": 30048, "target": 30034}], "30049": [], "30050": [{"count": 1, "source": 30050, "target": 30070}], "30051": [{"count": 1, "source": 30051, "target": 30067}], "30052": [{"count": 1, "source": 30052, "target": 30002}], "30053": [], "30054": [{"count": 1, "source": 30054, "target": 30002}], "30055": [], "30056": [], "30057": [{"count": 1, "source": 30057, "target": 30086}], "30058": [{"count": 1, "source": 30058, "target": 30099}], "30059": [{"count": 1, "source": 30059, "target": 30052}, {"count": 1, "source": 30059, "target": 30038}], "30060": [{"count": 1, "source": 30060, "target": 30032}, {"count": 1, "source": 30060, "target": 30066}], "30061": [], "30062": [{"count": 1, "source": 30062, "target": 30009}], "30063": [{"count": 1, "source": 30063, "target": 30031}], "30064": [], "30065": [], "30066": [{"count": 1, "source": 30066, "target": 30015}, {"count": 1, "source": 30066, "target": 30091}], "30067": [{"count": 1, "source": 30067, "target": 30020}, {"count": 1, "source": 30067, "target": 30094}], "30068": [{"count": 1, "source": 30068, "target": 30096}], "30069": [{"count": 1, "source": 30069, "target": 30004}], "30070": [], "30071": [{"count": 1, "source": 30071, "target": 30104}, {"count": 1, "source": 30071, "target": 30144}, {"count": 1, "source": 30071, "target": 30018}], "30072": [{"count": 1, "source": 30072, "target": 30016}], "30073": [], "30074": [], "30075": [{"count": 1, "source": 30075, "target": 30039}, {"count": 1, "source": 30075, "target": 30123}], "30076": [{"count": 1, "source": 30076, "target": 30033}], "30077": [{"count": 1, "source": 30077, "target": 30009}], "30078": [], "30079": [], "30080": [{"count": 1, "source": 30080, "target": 30010}], "30081": [{"count": 1, "source": 30081, "target": 30017}, {"count": 1, "source": 30081, "target": 30116}, {"count": 2, "source": 30081, "target": 30065}], "30083": [{"count": 1, "source": 30083, "target": 30023}], "30084": [{"count": 1, "source": 30084, "target": 30134}, {"count": 3, "source": 30084, "target": 30123}, {"count": 1, "source": 30084, "target": 30125}], "30085": [{"count": 1, "source": 30085, "target": 30051}, {"count": 1, "source": 30085, "target": 30117}, {"count": 1, "source": 30085, "target": 30008}, {"count": 1, "source": 30085, "target": 30136}], "30086": [{"count": 1, "source": 30086, "target": 30057}, {"count": 1, "source": 30086, "target": 30129}], "30087": [{"count": 1, "source": 30087, "target": 30098}], "30088": [{"count": 2, "source": 30088, "target": 30095}], "30089": [], "30090": [], "30091": [], "30092": [{"count": 2, "source": 30092, "target": 30083}], "30093": [{"count": 1, "source": 30093, "target": 30073}, {"count": 3, "source": 30093, "target": 30003}], "30094": [{"count": 1, "source": 30094, "target": 30026}], "30095": [{"count": 2, "source": 30095, "target": 30039}, {"count": 1, "source": 30095, "target": 30098}], "30096": [], "30097": [{"count": 2, "source": 30097, "target": 30091}], "30098": [], "30099": [], "30100": [{"count": 1, "source": 30100, "target": 30136}], "30101": [{"count": 1, "source": 30101, "target": 30129}], "30102": [{"count": 1, "source": 30102, "target": 30126}], "30103": [], "30104": [{"count": 1, "source": 30104, "target": 30078}, {"count": 1, "source": 30104, "target": 30017}, {"count": 1, "source": 30104, "target": 30040}, {"count": 1, "source": 30104, "target": 30010}], "30105": [{"count": 3, "source": 30105, "target": 30123}], "30106": [{"count": 1, "source": 30106, "target": 30027}, {"count": 2, "source": 30106, "target": 30118}], "30107": [{"count": 1, "source": 30107, "target": 30137}, {"count": 3, "source": 30107, "target": 30138}], "30108": [], "30109": [{"count": 1, "source": 30109, "target": 30079}, {"count": 1, "source": 30109, "target": 30120}], "30110": [{"count": 2, "source": 30110, "target": 30060}, {"count": 2, "source": 30110, "target": 30022}], "30111": [], "30112": [{"count": 1, "source": 30112, "target": 30051}], "30113": [], "30114": [{"count": 2, "source": 30114, "target": 30013}, {"count": 1, "source": 30114, "target": 30074}, {"count": 1, "source": 30114, "target": 30008}], "30115": [], "30116": [{"count": 1, "source": 30116, "target": 30080}, {"count": 1, "source": 30116, "target": 30090}], "30117": [], "30118": [], "30119": [{"count": 2, "source": 30119, "target": 30083}], "30120": [{"count": 1, "source": 30120, "target": 30123}, {"count": 1, "source": 30120, "target": 30109}], "30121": [{"count": 2, "source": 30121, "target": 30138}], "30122": [{"count": 1, "source": 30122, "target": 30113}, {"count": 1, "source": 30122, "target": 30008}, {"count": 2, "source": 30122, "target": 30134}], "30123": [{"count": 1, "source": 30123, "target": 30100}, {"count": 3, "source": 30123, "target": 30084}], "30124": [{"count": 1, "source": 30124, "target": 30073}], "30125": [{"count": 1, "source": 30125, "target": 30077}], "30126": [], "30127": [{"count": 1, "source": 30127, "target": 30086}, {"count": 1, "source": 30127, "target": 30083}], "30128": [{"count": 1, "source": 30128, "target": 30011}], "30129": [{"count": 1, "source": 30129, "target": 30137}, {"count": 1, "source": 30129, "target": 30100}], "30130": [], "30131": [], "30132": [], "30133": [], "30134": [], "30135": [{"count": 1, "source": 30135, "target": 30138}], "30136": [{"count": 2, "source": 30136, "target": 30040}], "30137": [], "30138": [{"count": 2, "source": 30138, "target": 30101}, {"count": 1, "source": 30138, "target": 30024}, {"count": 1, "source": 30138, "target": 30139}, {"count": 1, "source": 30138, "target": 30132}], "30139": [{"count": 1, "source": 30139, "target": 30130}, {"count": 1, "source": 30139, "target": 30122}, {"count": 1, "source": 30139, "target": 30116}, {"count": 1, "source": 30139, "target": 30100}], "30140": [{"count": 1, "source": 30140, "target": 30133}], "30141": [{"count": 1, "source": 30141, "target": 30138}], "30142": [], "30143": [{"count": 2, "source": 30143, "target": 30044}], "30144": [{"count": 1, "source": 30144, "target": 30072}], "30145": [{"count": 2, "source": 30145, "target": 30070}, {"count": 1, "source": 30145, "target": 30029}]}]