[{"30000": [{"count": 2, "source": 30000, "target": 30059}, {"count": 1, "source": 30000, "target": 30165}], "30001": [{"count": 1, "source": 30001, "target": 30144}, {"count": 2, "source": 30001, "target": 30100}], "30002": [{"count": 2, "source": 30002, "target": 30060}, {"count": 1, "source": 30002, "target": 30018}], "30003": [{"count": 1, "source": 30003, "target": 30168}], "30004": [{"count": 1, "source": 30004, "target": 30116}], "30005": [{"count": 1, "source": 30005, "target": 30073}, {"count": 1, "source": 30005, "target": 30003}, {"count": 1, "source": 30005, "target": 30161}], "30006": [{"count": 1, "source": 30006, "target": 30001}, {"count": 1, "source": 30006, "target": 30111}], "30007": [], "30008": [], "30009": [{"count": 1, "source": 30009, "target": 30124}, {"count": 2, "source": 30009, "target": 30059}, {"count": 1, "source": 30009, "target": 30160}, {"count": 1, "source": 30009, "target": 30073}], "30010": [], "30011": [], "30012": [{"count": 1, "source": 30012, "target": 30019}, {"count": 1, "source": 30012, "target": 30157}, {"count": 1, "source": 30012, "target": 30156}], "30013": [], "30014": [{"count": 1, "source": 30014, "target": 30108}, {"count": 1, "source": 30014, "target": 30109}], "30015": [{"count": 1, "source": 30015, "target": 30082}, {"count": 1, "source": 30015, "target": 30105}], "30016": [], "30017": [{"count": 2, "source": 30017, "target": 30002}, {"count": 1, "source": 30017, "target": 30072}], "30018": [{"count": 3, "source": 30018, "target": 30034}, {"count": 1, "source": 30018, "target": 30073}], "30019": [{"count": 2, "source": 30019, "target": 30163}, {"count": 1, "source": 30019, "target": 30092}], "30020": [{"count": 2, "source": 30020, "target": 30072}], "30021": [{"count": 1, "source": 30021, "target": 30073}, {"count": 1, "source": 30021, "target": 30168}, {"count": 1, "source": 30021, "target": 30054}], "30022": [{"count": 1, "source": 30022, "target": 30167}, {"count": 1, "source": 30022, "target": 30083}], "30023": [{"count": 1, "source": 30023, "target": 30012}, {"count": 1, "source": 30023, "target": 30061}], "30024": [{"count": 1, "source": 30024, "target": 30067}, {"count": 1, "source": 30024, "target": 30061}, {"count": 1, "source": 30024, "target": 30062}], "30025": [{"count": 2, "source": 30025, "target": 30079}, {"count": 2, "source": 30025, "target": 30052}, {"count": 1, "source": 30025, "target": 30080}], "30026": [{"count": 1, "source": 30026, "target": 30004}, {"count": 1, "source": 30026, "target": 30044}], "30027": [{"count": 2, "source": 30027, "target": 30155}, {"count": 2, "source": 30027, "target": 30152}], "30028": [{"count": 1, "source": 30028, "target": 30008}, {"count": 2, "source": 30028, "target": 30032}], "30029": [{"count": 3, "source": 30029, "target": 30026}], "30030": [{"count": 1, "source": 30030, "target": 30116}, {"count": 3, "source": 30030, "target": 30107}, {"count": 2, "source": 30030, "target": 30168}], "30031": [{"count": 1, "source": 30031, "target": 30097}], "30032": [{"count": 1, "source": 30032, "target": 30098}, {"count": 2, "source": 30032, "target": 30127}, {"count": 1, "source": 30032, "target": 30060}], "30033": [{"count": 2, "source": 30033, "target": 30148}], "30034": [], "30035": [{"count": 1, "source": 30035, "target": 30168}, {"count": 1, "source": 30035, "target": 30149}], "30036": [], "30037": [{"count": 1, "source": 30037, "target": 30164}, {"count": 2, "source": 30037, "target": 30091}], "30038": [], "30039": [{"count": 1, "source": 30039, "target": 30164}, {"count": 1, "source": 30039, "target": 30073}, {"count": 2, "source": 30039, "target": 30059}], "30040": [], "30041": [{"count": 1, "source": 30041, "target": 30057}], "30042": [], "30043": [], "30044": [{"count": 2, "source": 30044, "target": 30062}], "30045": [], "30046": [{"count": 2, "source": 30046, "target": 30127}, {"count": 1, "source": 30046, "target": 30148}, {"count": 1, "source": 30046, "target": 30070}], "30047": [{"count": 1, "source": 30047, "target": 30054}, {"count": 1, "source": 30047, "target": 30155}], "30048": [{"count": 1, "source": 30048, "target": 30097}], "30049": [{"count": 1, "source": 30049, "target": 30086}], "30050": [{"count": 1, "source": 30050, "target": 30038}], "30051": [], "30052": [], "30053": [{"count": 2, "source": 30053, "target": 30069}, {"count": 1, "source": 30053, "target": 30107}], "30054": [{"count": 1, "source": 30054, "target": 30021}, {"count": 2, "source": 30054, "target": 30012}, {"count": 1, "source": 30054, "target": 30066}, {"count": 3, "source": 30054, "target": 30156}, {"count": 1, "source": 30054, "target": 30011}], "30055": [{"count": 4, "source": 30055, "target": 30168}, {"count": 1, "source": 30055, "target": 30086}, {"count": 1, "source": 30055, "target": 30083}, {"count": 1, "source": 30055, "target": 30150}, {"count": 1, "source": 30055, "target": 30132}], "30056": [{"count": 2, "source": 30056, "target": 30161}], "30057": [{"count": 1, "source": 30057, "target": 30053}, {"count": 1, "source": 30057, "target": 30149}], "30058": [{"count": 1, "source": 30058, "target": 30048}], "30059": [{"count": 2, "source": 30059, "target": 30049}, {"count": 1, "source": 30059, "target": 30009}, {"count": 1, "source": 30059, "target": 30167}], "30060": [{"count": 1, "source": 30060, "target": 30148}], "30061": [{"count": 1, "source": 30061, "target": 30070}, {"count": 1, "source": 30061, "target": 30014}, {"count": 1, "source": 30061, "target": 30072}], "30062": [], "30063": [{"count": 1, "source": 30063, "target": 30123}], "30064": [], "30065": [{"count": 1, "source": 30065, "target": 30160}], "30066": [{"count": 1, "source": 30066, "target": 30010}], "30067": [{"count": 2, "source": 30067, "target": 30012}, {"count": 1, "source": 30067, "target": 30104}], "30068": [{"count": 1, "source": 30068, "target": 30021}, {"count": 1, "source": 30068, "target": 30152}, {"count": 1, "source": 30068, "target": 30065}], "30069": [{"count": 1, "source": 30069, "target": 30040}], "30070": [{"count": 1, "source": 30070, "target": 30089}, {"count": 1, "source": 30070, "target": 30021}, {"count": 1, "source": 30070, "target": 30092}], "30071": [], "30072": [], "30073": [{"count": 2, "source": 30073, "target": 30030}, {"count": 1, "source": 30073, "target": 30009}, {"count": 1, "source": 30073, "target": 30027}], "30074": [{"count": 2, "source": 30074, "target": 30049}, {"count": 1, "source": 30074, "target": 30118}, {"count": 1, "source": 30074, "target": 30054}, {"count": 1, "source": 30074, "target": 30148}, {"count": 1, "source": 30074, "target": 30050}], "30075": [{"count": 1, "source": 30075, "target": 30040}, {"count": 2, "source": 30075, "target": 30039}], "30076": [{"count": 1, "source": 30076, "target": 30026}], "30077": [], "30078": [{"count": 1, "source": 30078, "target": 30119}, {"count": 1, "source": 30078, "target": 30114}, {"count": 1, "source": 30078, "target": 30090}, {"count": 2, "source": 30078, "target": 30162}], "30079": [{"count": 1, "source": 30079, "target": 30088}], "30080": [{"count": 3, "source": 30080, "target": 30122}, {"count": 2, "source": 30080, "target": 30100}, {"count": 2, "source": 30080, "target": 30007}, {"count": 1, "source": 30080, "target": 30032}], "30081": [{"count": 1, "source": 30081, "target": 30039}, {"count": 1, "source": 30081, "target": 30140}, {"count": 2, "source": 30081, "target": 30142}, {"count": 1, "source": 30081, "target": 30138}], "30082": [{"count": 1, "source": 30082, "target": 30009}], "30083": [{"count": 1, "source": 30083, "target": 30123}, {"count": 1, "source": 30083, "target": 30157}, {"count": 1, "source": 30083, "target": 30031}], "30084": [{"count": 1, "source": 30084, "target": 30148}], "30085": [{"count": 1, "source": 30085, "target": 30154}, {"count": 1, "source": 30085, "target": 30134}], "30086": [{"count": 1, "source": 30086, "target": 30049}, {"count": 2, "source": 30086, "target": 30117}, {"count": 1, "source": 30086, "target": 30055}], "30087": [], "30088": [{"count": 1, "source": 30088, "target": 30012}, {"count": 1, "source": 30088, "target": 30003}, {"count": 1, "source": 30088, "target": 30077}, {"count": 1, "source": 30088, "target": 30156}], "30089": [], "30090": [{"count": 1, "source": 30090, "target": 30070}], "30091": [], "30092": [{"count": 1, "source": 30092, "target": 30019}], "30093": [{"count": 2, "source": 30093, "target": 30031}], "30094": [{"count": 1, "source": 30094, "target": 30148}], "30095": [{"count": 1, "source": 30095, "target": 30148}, {"count": 1, "source": 30095, "target": 30085}], "30096": [{"count": 2, "source": 30096, "target": 30154}], "30097": [{"count": 1, "source": 30097, "target": 30000}, {"count": 1, "source": 30097, "target": 30147}], "30098": [{"count": 2, "source": 30098, "target": 30041}], "30099": [], "30100": [{"count": 2, "source": 30100, "target": 30122}, {"count": 1, "source": 30100, "target": 30047}], "30101": [{"count": 1, "source": 30101, "target": 30006}, {"count": 1, "source": 30101, "target": 30060}], "30102": [{"count": 1, "source": 30102, "target": 30006}, {"count": 2, "source": 30102, "target": 30124}], "30103": [], "30104": [{"count": 1, "source": 30104, "target": 30151}, {"count": 2, "source": 30104, "target": 30163}, {"count": 1, "source": 30104, "target": 30067}, {"count": 1, "source": 30104, "target": 30062}], "30105": [{"count": 1, "source": 30105, "target": 30074}], "30106": [{"count": 1, "source": 30106, "target": 30129}], "30107": [], "30108": [], "30109": [{"count": 1, "source": 30109, "target": 30036}, {"count": 1, "source": 30109, "target": 30014}, {"count": 2, "source": 30109, "target": 30085}], "30110": [{"count": 3, "source": 30110, "target": 30014}, {"count": 1, "source": 30110, "target": 30145}], "30111": [{"count": 1, "source": 30111, "target": 30113}], "30112": [{"count": 1, "source": 30112, "target": 30019}, {"count": 1, "source": 30112, "target": 30076}, {"count": 3, "source": 30112, "target": 30042}], "30113": [], "30114": [{"count": 1, "source": 30114, "target": 30123}, {"count": 1, "source": 30114, "target": 30053}], "30115": [], "30116": [{"count": 2, "source": 30116, "target": 30164}], "30117": [], "30118": [], "30119": [], "30120": [{"count": 1, "source": 30120, "target": 30032}, {"count": 1, "source": 30120, "target": 30123}], "30121": [], "30122": [], "30123": [{"count": 1, "source": 30123, "target": 30102}, {"count": 1, "source": 30123, "target": 30164}, {"count": 1, "source": 30123, "target": 30131}, {"count": 1, "source": 30123, "target": 30135}], "30124": [{"count": 2, "source": 30124, "target": 30147}], "30125": [{"count": 1, "source": 30125, "target": 30124}], "30126": [], "30127": [{"count": 1, "source": 30127, "target": 30001}], "30128": [{"count": 1, "source": 30128, "target": 30144}], "30129": [], "30130": [{"count": 1, "source": 30130, "target": 30118}], "30131": [], "30132": [], "30133": [{"count": 2, "source": 30133, "target": 30124}, {"count": 1, "source": 30133, "target": 30134}], "30134": [{"count": 1, "source": 30134, "target": 30117}], "30135": [{"count": 1, "source": 30135, "target": 30010}], "30136": [{"count": 1, "source": 30136, "target": 30155}, {"count": 1, "source": 30136, "target": 30164}], "30137": [{"count": 2, "source": 30137, "target": 30155}, {"count": 1, "source": 30137, "target": 30129}], "30138": [{"count": 1, "source": 30138, "target": 30085}, {"count": 1, "source": 30138, "target": 30134}], "30139": [{"count": 2, "source": 30139, "target": 30086}, {"count": 1, "source": 30139, "target": 30113}, {"count": 1, "source": 30139, "target": 30100}], "30140": [], "30141": [{"count": 1, "source": 30141, "target": 30077}], "30142": [{"count": 5, "source": 30142, "target": 30003}, {"count": 1, "source": 30142, "target": 30067}], "30143": [], "30144": [{"count": 2, "source": 30144, "target": 30059}], "30145": [{"count": 2, "source": 30145, "target": 30092}], "30146": [{"count": 2, "source": 30146, "target": 30152}], "30147": [{"count": 2, "source": 30147, "target": 30123}, {"count": 1, "source": 30147, "target": 30092}, {"count": 1, "source": 30147, "target": 30093}], "30148": [{"count": 1, "source": 30148, "target": 30077}, {"count": 1, "source": 30148, "target": 30123}, {"count": 1, "source": 30148, "target": 30137}, {"count": 1, "source": 30148, "target": 30134}, {"count": 1, "source": 30148, "target": 30084}], "30149": [{"count": 2, "source": 30149, "target": 30123}], "30150": [{"count": 5, "source": 30150, "target": 30164}, {"count": 2, "source": 30150, "target": 30102}], "30151": [{"count": 1, "source": 30151, "target": 30022}, {"count": 1, "source": 30151, "target": 30027}, {"count": 4, "source": 30151, "target": 30069}, {"count": 1, "source": 30151, "target": 30054}], "30152": [{"count": 1, "source": 30152, "target": 30041}], "30153": [{"count": 1, "source": 30153, "target": 30036}, {"count": 1, "source": 30153, "target": 30046}], "30154": [{"count": 1, "source": 30154, "target": 30146}, {"count": 1, "source": 30154, "target": 30158}], "30155": [{"count": 1, "source": 30155, "target": 30038}, {"count": 2, "source": 30155, "target": 30110}, {"count": 2, "source": 30155, "target": 30123}, {"count": 2, "source": 30155, "target": 30027}, {"count": 1, "source": 30155, "target": 30158}], "30156": [{"count": 2, "source": 30156, "target": 30073}], "30157": [{"count": 1, "source": 30157, "target": 30039}], "30158": [{"count": 1, "source": 30158, "target": 30155}], "30159": [], "30160": [{"count": 1, "source": 30160, "target": 30023}, {"count": 4, "source": 30160, "target": 30034}, {"count": 1, "source": 30160, "target": 30065}, {"count": 1, "source": 30160, "target": 30092}], "30161": [{"count": 3, "source": 30161, "target": 30009}, {"count": 1, "source": 30161, "target": 30093}], "30162": [{"count": 2, "source": 30162, "target": 30122}], "30163": [{"count": 2, "source": 30163, "target": 30056}, {"count": 1, "source": 30163, "target": 30009}, {"count": 1, "source": 30163, "target": 30010}], "30164": [{"count": 1, "source": 30164, "target": 30013}, {"count": 1, "source": 30164, "target": 30137}, {"count": 1, "source": 30164, "target": 30103}], "30165": [{"count": 1, "source": 30165, "target": 30057}], "30166": [{"count": 1, "source": 30166, "target": 30042}, {"count": 1, "source": 30166, "target": 30149}, {"count": 1, "source": 30166, "target": 30092}], "30167": [], "30168": [{"count": 1, "source": 30168, "target": 30028}, {"count": 1, "source": 30168, "target": 30030}], "30169": [{"count": 1, "source": 30169, "target": 30039}, {"count": 3, "source": 30169, "target": 30007}]}]